{
    "id": "set_becomes_active_all",
    "title": {
        "en": "All states in set become active",
        "nl": "Alle statussen in set worden actief",
        "de": "Alle Zustände im Set werden aktiv",
        "fr": "Tous les états de l’ensemble deviennent actifs",
        "it": "Tutti gli stati nel set diventano attivi",
        "sv": "Alla tillstånd i uppsättningen blir aktiva",
        "no": "Alle tilstander i settet blir aktive",
        "es": "Todos los estados en el conjunto se activan",
        "da": "Alle tilstande i sættet bliver aktive",
        "ru": "Все состояния в наборе становятся активными",
        "pl": "Wszystkie stany w zestawie stają się aktywne",
        "ko": "세트의 모든 상태가 활성화됨",
        "ar": "تصبح جميع الحالات في المجموعة نشطة"
    },
    "titleFormatted": {
        "en": "All states in set [[set]] become active",
        "nl": "Alle statussen in set [[set]] worden actief",
        "de": "Alle Zustände im Set [[set]] werden aktiv",
        "fr": "Tous les états de l’ensemble [[set]] deviennent actifs",
        "it": "Tutti gli stati nel set [[set]] diventano attivi",
        "sv": "Alla tillstånd i uppsättningen [[set]] blir aktiva",
        "no": "Alle tilstander i settet [[set]] blir aktive",
        "es": "Todos los estados en el conjunto [[set]] se activan",
        "da": "Alle tilstande i sættet [[set]] bliver aktive",
        "ru": "Все состояния в наборе [[set]] становятся активными",
        "pl": "Wszystkie stany w zestawie [[set]] stają się aktywne",
        "ko": "세트 [[set]]의 모든 상태가 활성화됨",
        "ar": "تصبح جميع الحالات في المجموعة [[set]] نشطة"
    },
    "hint": {
        "en": "Triggers when all states in a set become active.",
        "nl": "Triggers wanneer alle statussen in een set actief worden.",
        "de": "Wird ausgelöst, wenn alle Zustände in einem Set aktiv werden.",
        "fr": "Se déclenche lorsque tous les états d’un ensemble deviennent actifs.",
        "it": "Si attiva quando tutti gli stati in un set diventano attivi.",
        "sv": "Utlöses när alla tillstånd i en uppsättning blir aktiva.",
        "no": "Utløses når alle tilstander i et sett blir aktive.",
        "es": "Se activa cuando todos los estados de un conjunto se activan.",
        "da": "Udløses når alle tilstande i et sæt bliver aktive.",
        "ru": "Срабатывает, когда все состояния в наборе становятся активными.",
        "pl": "Wyzwalane, gdy wszystkie stany w zestawie stają się aktywne.",
        "ko": "세트의 모든 상태가 활성화되면 트리거됩니다.",
        "ar": "يتم التشغيل عند تفعيل جميع الحالات في مجموعة."
    },
    "args": [
        {
            "type": "autocomplete",
            "name": "set",
            "title": {
                "en": "Set",
                "nl": "Set",
                "de": "Satz",
                "fr": "Ensemble",
                "it": "Set",
                "sv": "Uppsättning",
                "no": "Sett",
                "es": "Conjunto",
                "da": "Sæt",
                "ru": "Набор",
                "pl": "Zestaw",
                "ko": "세트",
                "ar": "مجموعة"
            }
        }
    ]
}
